RadeonMaster.py
RadeonMaster-0.1.0.dist-info/LICENSE
RadeonMaster-0.1.0.dist-info/METADATA
RadeonMaster-0.1.0.dist-info/WHEEL
RadeonMaster-0.1.0.dist-info/top_level.txt
RadeonMaster-0.1.0.dist-info/RECORD
