Metadata-Version: 2.1
Name: RadeonMaster
Version: 0.1.0
Summary: Radeon monitor for python
Home-page: https://github.com/MegalosVigneswaran/RadeonMaster
Author: Vigneswaran S
Author-email: contactmevigneswaran@gmail.com
Keywords: radeon gpu amd monitor linux radeontop
Classifier: Programming Language :: Python :: 3
Classifier: License :: OSI Approved :: MIT License
Classifier: Operating System :: POSIX :: Linux
Requires-Python: >=3.6
License-File: LICENSE
